PopularNews/__init__.py
popularnewsindonesia_dwikydamara-0.0.1.dist-info/METADATA
popularnewsindonesia_dwikydamara-0.0.1.dist-info/WHEEL
popularnewsindonesia_dwikydamara-0.0.1.dist-info/licenses/LICENSE
popularnewsindonesia_dwikydamara-0.0.1.dist-info/RECORD
